pytorch_seed/__init__.py
pytorch_seed-0.2.0.dist-info/LICENSE.txt
pytorch_seed-0.2.0.dist-info/METADATA
pytorch_seed-0.2.0.dist-info/WHEEL
pytorch_seed-0.2.0.dist-info/top_level.txt
pytorch_seed-0.2.0.dist-info/RECORD
