Metadata-Version: 2.1
Name: pytorch-seed
Version: 0.2.0
Summary: RNG seeding and context management for pytorch
Author-email: Sheng Zhong <zhsh@umich.edu>
Maintainer-email: Sheng Zhong <zhsh@umich.edu>
License: Copyright (c) 2023 University of Michigan ARM Lab
Project-URL: Homepage, https://github.com/UM-ARM-Lab/pytorch_seed
Project-URL: Bug Reports, https://github.com/UM-ARM-Lab/pytorch_seed/issues
Project-URL: Source, https://github.com/UM-ARM-Lab/pytorch_seed
Keywords: rng,pytorch,seeding,reproducibility
Classifier: Development Status :: 4 - Beta
Classifier: Intended Audience :: Developers
Classifier: License :: OSI Approved :: MIT License
Classifier: Programming Language :: Python :: 3
Classifier: Programming Language :: Python :: 3 :: Only
Requires-Python: >=3.6
Provides-Extra: test
License-File: LICENSE.txt
